xialib_pubsub/__init__.py
xialib_pubsub/pubsub_gcr_publisher.py
xialib_pubsub/pubsub_publisher.py
xialib_pubsub/pubsub_subscriber.py
xialib_pubsub-0.1.4.dist-info/LICENSE
xialib_pubsub-0.1.4.dist-info/METADATA
xialib_pubsub-0.1.4.dist-info/WHEEL
xialib_pubsub-0.1.4.dist-info/top_level.txt
xialib_pubsub-0.1.4.dist-info/RECORD
