Metadata-Version: 2.1
Name: xialib-pubsub
Version: 0.1.4
Summary: X-I-A Library - Google Cloud Storage Modules
Home-page: https://github.com/X-I-A/xialib-pubsub
Author: Soral
Author-email: soral@x-i-a.com
License: UNKNOWN
Platform: UNKNOWN
Classifier: Programming Language :: Python :: 3
Classifier: License :: OSI Approved :: GNU Affero General Public License v3 or later (AGPLv3+)
Classifier: Operating System :: OS Independent
Requires-Python: >=3.7
Requires-Dist: xialib
Requires-Dist: google-auth
Requires-Dist: google-cloud-pubsub
